논리회로/HW4/T_flip_flop.v
// 컴퓨터학부 심화컴퓨터전공 2020114658 이윤서 (LEE Yoon Seo)
// make module of T_flip flop

module T_flip_flop (Q, T, Clk, Rst_b);
    output Q;
    input T, Clk, Rst_b;
    reg Q;

    always @ (posedge Clk, negedge Rst_b)
        if (Rst_b == 0) Q <= 1'b0;
        else if (T) Q <= ~Q;
endmodule

논리회로/HW4/three_bit_binary_counter_B.v
// 컴퓨터학부 심화컴퓨터전공 2020114658 이윤서 (LEE Yoon Seo)

module three_bit_binary_counter_B (output [0:2] A, input Clk, clear);
    // declare wire and calculate
    wire TA;
    assign TA = A[1] || A[0];

    // match each of 3 Toggle flip flop 
    T_flip_flop M_A (A[0], 1'b1, Clk, clear);
    T_flip_flop M_B (A[1], A[0], Clk, clear);
    T_flip_flop M_C (A[2], TA, Clk, clear);

endmodule

논리회로/HW4/three_bit_binary_counter_A.v
// 컴퓨터학부 심화컴퓨터전공 2020114658 이윤서 (LEE Yoon Seo)

module three_bit_binary_counter_A (output[2:0] y_out, input Clk, clear);

    // declare var and constant var
    reg[2:0] state;
    // state
    parameter S0 = 3'b000, S1 = 3'b001, S2 = 3'b010, S3 = 3'b011, S4 = 3'b100, S5 = 3'b101, S6 = 3'b110, S7 = 3'b111;

    // execute when Clk(0->1) or clear(1->0) is change
    always @ (posedge Clk, negedge clear)
        // initialize state
        if (clear == 0) state <=S0;
        else case (state)
            // 3bit binary count
            S0 : state <= S1;
            S1 : state <= S2;
            S2 : state <= S3;
            S3 : state <= S4;
            S4 : state <= S5;
            S5 : state <= S6;
            S6 : state <= S7;
            S7 : state <= S0;
        endcase
    // set output
    assign y_out = state;
endmodule

논리회로/HW4/t_3_bit_binary_counter.v
// 컴퓨터학부 심화컴퓨터전공 2020114658 이윤서 (LEE Yoon Seo)


module t_3_bit_binary_counter;

    // declare input and output of testbench
    wire [2:0] t_A_y_out;
    wire [2:0] t_B_A;
    reg t_Clk, t_clear;

    // set the module for test
    three_bit_binary_counter_A MA(t_A_y_out,t_Clk,t_clear);
    three_bit_binary_counter_B MB(t_B_A, t_Clk,t_clear);

    // set finish time
    initial #300 $finish;

    initial begin
        // make wave file
        $dumpfile("2020114658.vcd");
        $dumpvars;

        // change var
        t_clear = 1'b0;
        t_Clk = 1'b0;
        #5 t_clear = 1'b1;c
        repeat(50)
            #5 t_Clk = ~t_Clk;
    end

    initial begin
        // print whenever var is change
        $monitor ("A2 A1 A0 = %b %b %b\tA2 A1 A0 = %b %b %b", t_A_y_out[2], t_A_y_out[1], t_A_y_out[0], t_B_A[2], t_B_A[1], t_B_A[0]);
    end
endmodule

논리회로/HW4/VCDfile.vcd
$date
	Thu Jun  3 21:56:19 2021
$end
$version
	Icarus Verilog
$end
$timescale
	1s
$end
$scope module t_3_bit_binary_counter $end
$var wire 3 ! t_B_A [2:0] $end
$var wire 3 " t_A_y_out [2:0] $end
$var reg 1 # t_Clk $end
$var reg 1 $ t_clear $end
$scope module MA $end
$var wire 1 # Clk $end
$var wire 1 $ clear $end
$var wire 3 % y_out [2:0] $end
$var reg 3 & state [2:0] $end
$upscope $end
$scope module MB $end
$var wire 1 # Clk $end
$var wire 1 ' TA $end
$var wire 1 $ clear $end
$var wire 3 ( A [0:2] $end
$scope module M_A $end
$var wire 1 # Clk $end
$var wire 1 $ Rst_b $end
$var wire 1 ) T $end
$var reg 1 * Q $end
$upscope $end
$scope module M_B $end
$var wire 1 # Clk $end
$var wire 1 $ Rst_b $end
$var wire 1 + T $end
$var reg 1 , Q $end
$upscope $end
$scope module M_C $end
$var wire 1 # Clk $end
$var wire 1 $ Rst_b $end
$var wire 1 ' T $end
$var reg 1 - Q $end
$upscope $end
$upscope $end
$upscope $end
$enddefinitions $end
#0
$dumpvars
0-
0,
0+
0*
1)
b0 (
0'
b0 &
b0 %
0$
0#
b0 "
b0 !
$end
#5
1$
#10
1'
1+
b100 !
b100 (
1*
b1 "
b1 %
b1 &
1#
#15
0#
#20
0+
b10 "
b10 %
b10 &
0*
1,
b11 !
b11 (
1-
1#
#25
0#
#30
1+
0-
b110 !
b110 (
1*
b11 "
b11 %
b11 &
1#
#35
0#
#40
0'
0+
b100 "
b100 %
b100 &
0*
0,
b1 !
b1 (
1-
1#
#45
0#
#50
1'
1+
b101 !
b101 (
1*
b101 "
b101 %
b101 &
1#
#55
0#
#60
0+
b110 "
b110 %
b110 &
0*
1,
b10 !
b10 (
0-
1#
#65
0#
#70
1+
1-
b111 !
b111 (
1*
b111 "
b111 %
b111 &
1#
#75
0#
#80
0'
0+
b0 "
b0 %
b0 &
0*
0,
b0 !
b0 (
0-
1#
#85
0#
#90
1'
1+
b100 !
b100 (
1*
b1 "
b1 %
b1 &
1#
#95
0#
#100
0+
b10 "
b10 %
b10 &
0*
1,
b11 !
b11 (
1-
1#
#105
0#
#110
1+
0-
b110 !
b110 (
1*
b11 "
b11 %
b11 &
1#
#115
0#
#120
0'
0+
b100 "
b100 %
b100 &
0*
0,
b1 !
b1 (
1-
1#
#125
0#
#130
1'
1+
b101 !
b101 (
1*
b101 "
b101 %
b101 &
1#
#135
0#
#140
0+
b110 "
b110 %
b110 &
0*
1,
b10 !
b10 (
0-
1#
#145
0#
#150
1+
1-
b111 !
b111 (
1*
b111 "
b111 %
b111 &
1#
#155
0#
#160
0'
0+
b0 "
b0 %
b0 &
0*
0,
b0 !
b0 (
0-
1#
#165
0#
#170
1'
1+
b100 !
b100 (
1*
b1 "
b1 %
b1 &
1#
#175
0#
#180
0+
b10 "
b10 %
b10 &
0*
1,
b11 !
b11 (
1-
1#
#185
0#
#190
1+
0-
b110 !
b110 (
1*
b11 "
b11 %
b11 &
1#
#195
0#
#200
0'
0+
b100 "
b100 %
b100 &
0*
0,
b1 !
b1 (
1-
1#
#205
0#
#210
1'
1+
b101 !
b101 (
1*
b101 "
b101 %
b101 &
1#
#215
0#
#220
0+
b110 "
b110 %
b110 &
0*
1,
b10 !
b10 (
0-
1#
#225
0#
#230
1+
1-
b111 !
b111 (
1*
b111 "
b111 %
b111 &
1#
#235
0#
#240
0'
0+
b0 "
b0 %
b0 &
0*
0,
b0 !
b0 (
0-
1#
#245
0#
#250
1'
1+
b100 !
b100 (
1*
b1 "
b1 %
b1 &
1#
